stappy/__init__.py
stappy-0.0.4.dist-info/LICENSE
stappy-0.0.4.dist-info/METADATA
stappy-0.0.4.dist-info/WHEEL
stappy-0.0.4.dist-info/top_level.txt
stappy-0.0.4.dist-info/RECORD
