Metadata-Version: 2.1
Name: stappy
Version: 0.0.4
Summary: a storage-access protocol for python
Home-page: https://github.com/gwappa/python-stappy
Author: Keisuke Sehara
Author-email: keisuke.sehara@gmail.com
License: MIT
Platform: UNKNOWN
Classifier: Development Status :: 3 - Alpha
Classifier: License :: OSI Approved :: MIT License
Classifier: Programming Language :: Python :: 3
Requires-Dist: numpy (>=1.0)
